intelligraphs/__init__.py
intelligraphs/info.py
intelligraphs/baseline_models/__init__.py
intelligraphs/baseline_models/knowledge_graph_embedding_model.py
intelligraphs/baseline_models/scoring_functions.py
intelligraphs/baseline_models/uniform_baseline_model.py
intelligraphs/baseline_models/utils.py
intelligraphs/data_loaders/__init__.py
intelligraphs/data_loaders/download.py
intelligraphs/data_loaders/loaders.py
intelligraphs/data_loaders/loading_functions.py
intelligraphs/data_loaders/utils.py
intelligraphs/data_validation/__init__.py
intelligraphs/data_validation/validate_data.py
intelligraphs/domains/__init__.py
intelligraphs/domains/SynPaths/__init__.py
intelligraphs/domains/SynPaths/entities.py
intelligraphs/domains/SynPaths/relations.py
intelligraphs/domains/SynTIPR/__init__.py
intelligraphs/domains/SynTIPR/entities.py
intelligraphs/domains/SynTIPR/relations.py
intelligraphs/domains/SynTypes/__init__.py
intelligraphs/domains/SynTypes/entities.py
intelligraphs/domains/SynTypes/relations.py
intelligraphs/domains/WDArticles/__init__.py
intelligraphs/domains/WDArticles/entities.py
intelligraphs/domains/WDArticles/relations.py
intelligraphs/domains/WDMovies/__init__.py
intelligraphs/domains/WDMovies/entities.py
intelligraphs/domains/WDMovies/relations.py
intelligraphs/errors/__init__.py
intelligraphs/errors/custom_error.py
intelligraphs/evaluators/__init__.py
intelligraphs/evaluators/evaluation_functions.py
intelligraphs/evaluators/post_processing.py
intelligraphs/evaluators/semantic_checker.py
intelligraphs/generators/__init__.py
intelligraphs/generators/synthetic/__init__.py
intelligraphs/generators/synthetic/dataset_generator_base.py
intelligraphs/generators/synthetic/synpaths_generator.py
intelligraphs/generators/synthetic/syntipr_generator.py
intelligraphs/generators/synthetic/syntypes_generator.py
intelligraphs/generators/wikidata/__init__.py
intelligraphs/generators/wikidata/wdarticles_generator.py
intelligraphs/generators/wikidata/wdmovies_generator.py
intelligraphs-1.0.18.dist-info/LICENSE
intelligraphs-1.0.18.dist-info/METADATA
intelligraphs-1.0.18.dist-info/WHEEL
intelligraphs-1.0.18.dist-info/top_level.txt
intelligraphs-1.0.18.dist-info/RECORD
