Metadata-Version: 2.2
Name: intelligraphs
Version: 1.0.18
Summary: A Python package for using IntelliGraphs benchmarking datasets.
Home-page: https://github.com/thiviyanT/intelligraphs
Author: Thiviyan Thanapalasingam
Author-email: thiviyan.t@gmail.com
Classifier: Development Status :: 3 - Alpha
Classifier: Intended Audience :: Developers
Classifier: License :: OSI Approved :: MIT License
Classifier: Programming Language :: Python :: 3
Classifier: Programming Language :: Python :: 3.8
Classifier: Programming Language :: Python :: 3.9
Requires-Python: >=3.7
License-File: LICENSE
Requires-Dist: tqdm
Requires-Dist: bokeh
Requires-Dist: graphviz
Requires-Dist: requests
Requires-Dist: torch
Requires-Dist: seaborn
Requires-Dist: matplotlib
Requires-Dist: scipy
Requires-Dist: numpy==1.26.4
Dynamic: author
Dynamic: author-email
Dynamic: classifier
Dynamic: description
Dynamic: description-content-type
Dynamic: home-page
Dynamic: requires-dist
Dynamic: requires-python
Dynamic: summary
